VisOpy/Zernike.py
VisOpy/__init__.py
VisOpy/aberturas.py
VisOpy/formacion.py
VisOpy/propagacion.py
VisOpy/transmitancia.py
VisOpy-0.1.2.dist-info/METADATA
VisOpy-0.1.2.dist-info/WHEEL
VisOpy-0.1.2.dist-info/top_level.txt
VisOpy-0.1.2.dist-info/RECORD
