Metadata-Version: 2.1
Name: VisOpy
Version: 0.1.2
Summary: Simulacion de un sistema optico
Home-page: https://www.instagram.com/salo_mei343/
Author: Salo <3
Author-email: salome.osoriom@udea.edu.co
License: MIT
Requires-Python: >=3.11.2
Requires-Dist: numpy ==1.26.1
Requires-Dist: matplotlib ==3.8.1
Requires-Dist: scipy ==1.11.3
Requires-Dist: Pillow ==10.1.0
